pygz/__init__.py
pygz/gzip.py
pygz/pigz.py
pygz-1.0.1.dist-info/LICENSE
pygz-1.0.1.dist-info/METADATA
pygz-1.0.1.dist-info/WHEEL
pygz-1.0.1.dist-info/top_level.txt
pygz-1.0.1.dist-info/RECORD
