Metadata-Version: 2.1
Name: pygz
Version: 1.0.1
Summary: A wrapper for gzip and pigz in python
Home-page: https://gitee.com/chenzonggui/pygz
Author: Zonggui Chen
Author-email: ggchenzonggui@qq.com
License: UNKNOWN
Platform: UNKNOWN
Classifier: Programming Language :: Python :: 3
Classifier: License :: OSI Approved :: MIT License
Classifier: Operating System :: Unix
Requires-Python: >=3.6
License-File: LICENSE
